esa_apex_toolbox/__init__.py
esa_apex_toolbox/_about.py
esa_apex_toolbox/algorithms.py
esa_apex_algorithms-0.0.1.dist-info/METADATA
esa_apex_algorithms-0.0.1.dist-info/WHEEL
esa_apex_algorithms-0.0.1.dist-info/licenses/LICENSE
esa_apex_algorithms-0.0.1.dist-info/RECORD
