Metadata-Version: 2.4
Name: esa-apex-algorithms
Version: 0.0.1
Summary: Python toolbox to interact with ESA APEx algorithm catalog.
Project-URL: Homepage, https://github.com/ESA-APEx/apex_algorithms
Project-URL: Issues, https://github.com/ESA-APEx/apex_algorithms/issues
Author-email: Stefaan Lippens <stefaan.lippens@vito.be>
License:                                  Apache License
License-File: LICENSE
Keywords: EO,ESA,Earth observation,openEO
Classifier: Development Status :: 3 - Alpha
Classifier: License :: OSI Approved :: Apache Software License
Classifier: Programming Language :: Python :: 3
Requires-Python: >=3.8
Requires-Dist: requests>=2.30.0
Provides-Extra: dev
Requires-Dist: pytest>=8.2.0; extra == 'dev'
Requires-Dist: requests-mock>=1.12.0; extra == 'dev'
Provides-Extra: tests
Requires-Dist: pytest>=8.2.0; extra == 'tests'
Requires-Dist: requests-mock>=1.12.0; extra == 'tests'
